image_utils/__init__.py
image_utils/get.py
json_utils/__init__.py
json_utils/get.py
web_utils_soft-0.4.1.dist-info/LICENSE
web_utils_soft-0.4.1.dist-info/METADATA
web_utils_soft-0.4.1.dist-info/WHEEL
web_utils_soft-0.4.1.dist-info/top_level.txt
web_utils_soft-0.4.1.dist-info/RECORD
